{
  "request_info": {
    "success": true,
    "credits_used": 2761,
    "credits_used_this_request": 1,
    "credits_remaining": 7239,
    "credits_reset_at": "2025-09-14T15:57:58.000Z"
  },
  "request_parameters": {
    "source": "walmart",
    "walmart_domain": "walmart.com",
    "type": "product",
    "item_id": "16835722144"
  },
  "request_metadata": {
    "created_at": "2025-09-01T04:39:02.960Z",
    "processed_at": "2025-09-01T04:39:08.422Z",
    "total_time_taken": 5.46,
    "walmart_url": "https://www.walmart.com/ip/16835722144"
  },
  "product": {
    "brand": "Nike",
    "link": "https://www.walmart.com/ip/Nike-Men-s-Dunk-Low-Vintage-Coral-from-StockX/16835722144",
    "title": "Nike Men's Dunk Low Vintage Coral, from StockX",
    "upc": "469014976044",
    "item_id": "16835722144",
    "product_id": "HQ4988-030",
    "item_number": "6HGCZRBDQV0O",
    "description": "As part of this partnership with Walmart, StockX has a 14 day return policy and the item must be in original, new condition with the StockX tag attached",
    "description_html": "As part of this partnership with Walmart, StockX has a 14 day return policy and the item must be in original, new condition with the StockX tag attached",
    "description_full": "* Nike Men's Dunk Low Vintage Coral - HQ4988-030 - 11\n * Style code: HQ4988-030\n * Colorway: Phantom/Black/Vintage Coral/Pale Ivory\n * This item comes verified by StockX, brand new with tags\n * As part of this partnership with Walmart, StockX has a 14 day return policy and the item must be in original, new condition with the StockX tag attached\n * Items shipped from StockX are part of the Xpress Ship program which will ship out within 1 business day\n * Sneaker boxes will be original and in good condition. They may have minor cosmetic damage that could occur from the manufacturer, shipping, and storage\n * Shipping fee is included in the add to cart price for StockX items",
    "description_full_html": "<ul>  <li>Nike Men's Dunk Low Vintage Coral - HQ4988-030 - 11</li>  <li>Style code: HQ4988-030</li>  <li>Colorway: Phantom/Black/Vintage Coral/Pale Ivory</li>  <li>This item comes verified by StockX, brand new with tags</li>  <li>As part of this partnership with Walmart, StockX has a 14 day return policy and the item must be in original, new condition with the StockX tag attached</li>  <li>Items shipped from StockX are part of the Xpress Ship program which will ship out within 1 business day</li>  <li>Sneaker boxes will be original and in good condition. They may have minor cosmetic damage that could occur from the manufacturer, shipping, and storage</li>  <li>Shipping fee is included in the add to cart price for StockX items</li> </ul>",
    "model": "Dunk Low",
    "ratings_total": 1,
    "rating": 5,
    "type": "Athletic Shoes",
    "main_image": {
      "link": "https://i5.walmartimages.com/seo/Nike-Men-s-Dunk-Low-Vintage-Coral-from-StockX_13b375f4-179f-4544-b224-406468da1bc3.40bb4f94d1dcc0b9af0cb2e76df0820d.jpeg"
    },
    "images": [
      {
        "link": "https://i5.walmartimages.com/seo/Nike-Men-s-Dunk-Low-Vintage-Coral-from-StockX_13b375f4-179f-4544-b224-406468da1bc3.40bb4f94d1dcc0b9af0cb2e76df0820d.jpeg",
        "id": "3AE4C10DCBB848AF89CBDB73A260C5CC",
        "zoomable": true
      },
      {
        "link": "https://i5.walmartimages.com/asr/ab5e0711-9c07-4ffd-a4ab-ed1c7c513780.f1e6aff5ff05510ee9501ad5b2707e46.jpeg",
        "id": "A0B73908A66D4149BC008C18B55621A8",
        "zoomable": true
      },
      {
        "link": "https://i5.walmartimages.com/asr/6b766f63-9951-4c38-a55e-104f8adf5e99.d140a865b57e366c5892fa56f4cb9b76.jpeg",
        "id": "958B72CA1E814EDCB327F9FC6AB2C314",
        "zoomable": true
      },
      {
        "link": "https://i5.walmartimages.com/asr/16f2d21b-eb9e-4c7c-a1aa-62e734f3e532.f151af20640b0d08df7b466c384cd8c3.jpeg",
        "id": "80C17D171BF646319602B1E4DBABB289",
        "zoomable": true
      },
      {
        "link": "https://i5.walmartimages.com/asr/f53702ed-398d-46dc-addc-9c8291cbadf2.651b70c7bde351f0544e518675e30169.jpeg",
        "id": "50425D570705423A8D58C22CF52F8EF8",
        "zoomable": true
      }
    ],
    "breadcrumbs": [
      {
        "name": "Clothing",
        "link": "https://www.walmart.com/cp/clothing/5438"
      },
      {
        "name": "Shoes",
        "link": "https://www.walmart.com/cp/shoes/1045804"
      },
      {
        "name": "Mens Shoes",
        "link": "https://www.walmart.com/cp/mens-shoes/1045807"
      },
      {
        "name": "Mens Sneakers",
        "link": "https://www.walmart.com/cp/mens-sneakers/3383528"
      },
      {
        "name": "Mens Casual Sneakers",
        "link": "https://www.walmart.com/cp/mens-casual-sneakers/1662705"
      }
    ],
    "specifications": [
      {
        "name": "Shoe Category",
        "value": "Men's Shoes"
      },
      {
        "name": "Gender",
        "value": "Male"
      },
      {
        "name": "Manufacturer Part Number",
        "value": "HQ4988-030"
      },
      {
        "name": "Brand",
        "value": "Nike"
      }
    ],
    "buybox_winner": {
      "price": 94,
      "currency_symbol": "$",
      "id": "816B0C149AF0372C9F057756B5467520",
      "seller": {
        "name": "StockX",
        "id_secondary": "D00FBAB3A90E4243BCAF938753A7663B",
        "id": 102524329,
        "link": "https://www.walmart.com/seller/102524329"
      },
      "fulfillment": {
        "pickup": false,
        "delivery_from_store": false,
        "shipping": true,
        "shipping_message": "Free shipping, arrives by Fri, Sep 5 to Miami, 33130",
        "message": "Free shipping, arrives by Fri, Sep 5 to Miami, 33130",
        "zipcode": "33130"
      },
      "availability": {
        "raw": "IN_STOCK",
        "in_stock": true,
        "preorder": false
      },
      "shipping": {
        "raw": "FREE"
      },
      "return_policy": {
        "duration_days": 30,
        "type": "Day",
        "seller": "StockX"
      }
    },
    "variants": [
      {
        "item_id": "16835722144",
        "product_id": "6HGCZRBDQV0O",
        "link": "https://www.walmart.com/ip/16835722144",
        "in_stock": true,
        "price": 94,
        "images": [
          {
            "link": "https://i5.walmartimages.com/seo/Nike-Men-s-Dunk-Low-Vintage-Coral-from-StockX_13b375f4-179f-4544-b224-406468da1bc3.40bb4f94d1dcc0b9af0cb2e76df0820d.jpeg",
            "id": "3AE4C10DCBB848AF89CBDB73A260C5CC",
            "zoomable": true
          },
          {
            "link": "https://i5.walmartimages.com/asr/ab5e0711-9c07-4ffd-a4ab-ed1c7c513780.f1e6aff5ff05510ee9501ad5b2707e46.jpeg",
            "id": "A0B73908A66D4149BC008C18B55621A8",
            "zoomable": true
          },
          {
            "link": "https://i5.walmartimages.com/asr/6b766f63-9951-4c38-a55e-104f8adf5e99.d140a865b57e366c5892fa56f4cb9b76.jpeg",
            "id": "958B72CA1E814EDCB327F9FC6AB2C314",
            "zoomable": true
          },
          {
            "link": "https://i5.walmartimages.com/asr/16f2d21b-eb9e-4c7c-a1aa-62e734f3e532.f151af20640b0d08df7b466c384cd8c3.jpeg",
            "id": "80C17D171BF646319602B1E4DBABB289",
            "zoomable": true
          },
          {
            "link": "https://i5.walmartimages.com/asr/f53702ed-398d-46dc-addc-9c8291cbadf2.651b70c7bde351f0544e518675e30169.jpeg",
            "id": "50425D570705423A8D58C22CF52F8EF8",
            "zoomable": true
          }
        ],
        "criteria": [
          {
            "name": "actual_color",
            "value": "phantom/black/vintagecoral/paleivory"
          },
          {
            "name": "shoe_size",
            "value": "11"
          }
        ]
      },
      {
        "item_id": "16935353535",
        "product_id": "35IG2WRBDP3T",
        "link": "https://www.walmart.com/ip/16935353535",
        "in_stock": false,
        "price": 92,
        "criteria": [
          {
            "name": "actual_color",
            "value": "phantom/black/vintagecoral/paleivory"
          },
          {
            "name": "shoe_size",
            "value": "10.5"
          }
        ]
      },
      {
        "item_id": "16967055797",
        "product_id": "0UO4YK0JG4Y7",
        "link": "https://www.walmart.com/ip/16967055797",
        "in_stock": false,
        "price": 76,
        "criteria": [
          {
            "name": "actual_color",
            "value": "phantom/black/vintagecoral/paleivory"
          },
          {
            "name": "shoe_size",
            "value": "8"
          }
        ]
      },
      {
        "item_id": "16936811539",
        "product_id": "2R0EK3XW5SG5",
        "link": "https://www.walmart.com/ip/16936811539",
        "in_stock": false,
        "price": 94,
        "criteria": [
          {
            "name": "actual_color",
            "value": "phantom/black/vintagecoral/paleivory"
          },
          {
            "name": "shoe_size",
            "value": "9"
          }
        ]
      },
      {
        "item_id": "16817916610",
        "product_id": "1X9IIDG7IRLD",
        "link": "https://www.walmart.com/ip/16817916610",
        "in_stock": false,
        "price": 94,
        "criteria": [
          {
            "name": "actual_color",
            "value": "phantom/black/vintagecoral/paleivory"
          },
          {
            "name": "shoe_size",
            "value": "10"
          }
        ]
      },
      {
        "item_id": "16907601093",
        "product_id": "7BJFKYXAPU75",
        "link": "https://www.walmart.com/ip/16907601093",
        "in_stock": true,
        "price": 106,
        "criteria": [
          {
            "name": "actual_color",
            "value": "phantom/black/vintagecoral/paleivory"
          },
          {
            "name": "shoe_size",
            "value": "6.5"
          }
        ]
      },
      {
        "item_id": "16843251444",
        "product_id": "286CUV22BCVU",
        "link": "https://www.walmart.com/ip/16843251444",
        "in_stock": true,
        "price": 94,
        "criteria": [
          {
            "name": "actual_color",
            "value": "phantom/black/vintagecoral/paleivory"
          },
          {
            "name": "shoe_size",
            "value": "9.5"
          }
        ]
      },
      {
        "item_id": "16834173986",
        "product_id": "4VBMDPFREKUF",
        "link": "https://www.walmart.com/ip/16834173986",
        "in_stock": false,
        "price": 91,
        "criteria": [
          {
            "name": "actual_color",
            "value": "phantom/black/vintagecoral/paleivory"
          },
          {
            "name": "shoe_size",
            "value": "8.5"
          }
        ]
      },
      {
        "item_id": "16958656010",
        "product_id": "16XN2PX2YR4M",
        "link": "https://www.walmart.com/ip/16958656010",
        "in_stock": false,
        "price": 95,
        "criteria": [
          {
            "name": "actual_color",
            "value": "phantom/black/vintagecoral/paleivory"
          },
          {
            "name": "shoe_size",
            "value": "12"
          }
        ]
      },
      {
        "item_id": "17295170126",
        "product_id": "3SBPECAIUJ00",
        "link": "https://www.walmart.com/ip/17295170126",
        "in_stock": false,
        "price": 82,
        "criteria": [
          {
            "name": "actual_color",
            "value": "phantom/black/vintagecoral/paleivory"
          },
          {
            "name": "shoe_size",
            "value": "14"
          }
        ]
      }
    ]
  },
  "location_info": {
    "city": "Miami",
    "state": "FL",
    "zipcode": "33130",
    "store_id": "4303"
  }
}